googleapiutils2/__init__.py
googleapiutils2/monitor.py
googleapiutils2/py.typed
googleapiutils2/admin/__init__.py
googleapiutils2/admin/admin.py
googleapiutils2/drive/__init__.py
googleapiutils2/drive/drive.py
googleapiutils2/drive/misc.py
googleapiutils2/geocode/__init__.py
googleapiutils2/geocode/geocode.py
googleapiutils2/geocode/misc.py
googleapiutils2/groups/__init__.py
googleapiutils2/groups/groups.py
googleapiutils2/groups/misc.py
googleapiutils2/mail/__init__.py
googleapiutils2/mail/mail.py
googleapiutils2/sheets/__init__.py
googleapiutils2/sheets/misc.py
googleapiutils2/sheets/sheets.py
googleapiutils2/sheets/sheets_slice.py
googleapiutils2/sheets/sheets_value_range.py
googleapiutils2/utils/__init__.py
googleapiutils2/utils/decorators.py
googleapiutils2/utils/drive.py
googleapiutils2/utils/misc.py
googleapiutils2/utils/utils.py
googleapiutils2-0.20.0.dist-info/METADATA
googleapiutils2-0.20.0.dist-info/WHEEL
googleapiutils2-0.20.0.dist-info/licenses/LICENSE
googleapiutils2-0.20.0.dist-info/RECORD
