Metadata-Version: 2.4
Name: googleapiutils2
Version: 0.20.0
Summary: Wrapper for Google's Python API
Project-URL: Repository, https://github.com/mkbabb/googleapiutils2
Project-URL: Bug Tracker, https://github.com/mkbabb/googleapiutils2/issues
Author-email: Mike Babb <mike7400@gmail.com>
License: MIT
License-File: LICENSE
Keywords: google,google api,google-api,google-drive-api,google-sheets-api,googleapi,googleapiutils2
Classifier: Development Status :: 4 - Beta
Classifier: Intended Audience :: Developers
Classifier: License :: OSI Approved :: MIT License
Classifier: Operating System :: OS Independent
Classifier: Programming Language :: Python :: 3
Classifier: Programming Language :: Python :: 3.12
Classifier: Programming Language :: Python :: 3.13
Classifier: Topic :: Internet :: WWW/HTTP
Classifier: Topic :: Software Development :: Libraries :: Python Modules
Requires-Python: >=3.12
Requires-Dist: cachetools>=5.5.2
Requires-Dist: google-api-python-client-stubs>=1.30.0
Requires-Dist: google-api-python-client>=2.168.0
Requires-Dist: google-auth-httplib2>=0.2.0
Requires-Dist: google-auth-oauthlib>=1.2.1
Requires-Dist: google-auth>=2.39.0
Requires-Dist: loguru>=0.7.3
Requires-Dist: openpyxl>=3.1.5
Requires-Dist: pandas>=2.2.3
Requires-Dist: pydantic>=2.11.2
Requires-Dist: requests>=2.32.3
Provides-Extra: dev
Requires-Dist: anthropic>=0.60.0; extra == 'dev'
Requires-Dist: ipinfo>=5.2.0; extra == 'dev'
Requires-Dist: jinja2>=3.1.6; extra == 'dev'
Requires-Dist: litellm>=1.74.15.post1; extra == 'dev'
Requires-Dist: markdown2>=2.5.4; extra == 'dev'
Requires-Dist: mypy>=1.17.1; extra == 'dev'
Requires-Dist: openai>=1.98.0; extra == 'dev'
Requires-Dist: pandas-stubs>=2.3.0.250703; extra == 'dev'
Requires-Dist: pillow>=11.3.0; extra == 'dev'
Requires-Dist: pyarrow>=21.0.0; extra == 'dev'
Requires-Dist: pymupdf>=1.26.3; extra == 'dev'
Requires-Dist: pypdf>=5.9.0; extra == 'dev'
Requires-Dist: pytest>=8.4.1; extra == 'dev'
Requires-Dist: ruff>=0.12.7; extra == 'dev'
Requires-Dist: types-cachetools>=6.1.0.20250717; extra == 'dev'
Requires-Dist: types-requests>=2.32.4.20250611; extra == 'dev'
